[
  {
    "E_ID": 1.0,
    "E_NAME": "Vidovic",
    "USER_NAME": "vdoorey0",
    "PASSWORD": "eV4_lMRcA",
    "PHONE_NO": "114-211-4290",
    "EMAIL": "vmulholland0@slate.com",
    "ADDRESS": "Room 1560",
    "JOIN_DATE": "8/5/2023 00:00:00",
    "PHOTO": "https://robohash.org/iustoblanditiissimilique.png?size=50x50&set=set1"
  },
  {
    "E_ID": 2.0,
    "E_NAME": "Berta",
    "USER_NAME": "bpiola1",
    "PASSWORD": "tT3_A\"6tlSVyD",
    "PHONE_NO": "760-226-2106",
    "EMAIL": "bsimonin1@nifty.com",
    "ADDRESS": "Suite 75",
    "JOIN_DATE": "30/5/2022 00:00:00",
    "PHOTO": "https://robohash.org/quisimpeditquibusdam.png?size=50x50&set=set1"
  },
  {
    "E_ID": 3.0,
    "E_NAME": "Kingsley",
    "USER_NAME": "kmorson2",
    "PASSWORD": "qZ1,cZ1c3",
    "PHONE_NO": "401-555-6642",
    "EMAIL": "ksenechault2@youku.com",
    "ADDRESS": "Apt 1008",
    "JOIN_DATE": "7/6/2022 00:00:00",
    "PHOTO": "https://robohash.org/etquaecumque.png?size=50x50&set=set1"
  },
  {
    "E_ID": 4.0,
    "E_NAME": "Trude",
    "USER_NAME": "tbiever3",
    "PASSWORD": "iG4*=\\<T3qG",
    "PHONE_NO": "943-305-2657",
    "EMAIL": "thassur3@fastcompany.com",
    "ADDRESS": "Room 290",
    "JOIN_DATE": "27/4/2023 00:00:00",
    "PHOTO": "https://robohash.org/animioccaecatiqui.png?size=50x50&set=set1"
  },
  {
    "E_ID": 5.0,
    "E_NAME": "Honor",
    "USER_NAME": "hwybrow4",
    "PASSWORD": "wS0~0T}c~",
    "PHONE_NO": "360-641-6093",
    "EMAIL": "hgabbetis4@e-recht24.de",
    "ADDRESS": "PO Box 90782",
    "JOIN_DATE": "4/2/2022 00:00:00",
    "PHOTO": "https://robohash.org/doloremautoptio.png?size=50x50&set=set1"
  },
  {
    "E_ID": 6.0,
    "E_NAME": "Jannel",
    "USER_NAME": "julyet5",
    "PASSWORD": "bD3_Ak(gMS",
    "PHONE_NO": "305-583-9245",
    "EMAIL": "jgowland5@lycos.com",
    "ADDRESS": "Suite 7",
    "JOIN_DATE": "10/9/2022 00:00:00",
    "PHOTO": "https://robohash.org/hicvoluptateminventore.png?size=50x50&set=set1"
  },
  {
    "E_ID": 7.0,
    "E_NAME": "Irena",
    "USER_NAME": "ifaughnan6",
    "PASSWORD": "zY1,ewN>ZC2Ai/m9",
    "PHONE_NO": "500-429-8583",
    "EMAIL": "inother6@ifeng.com",
    "ADDRESS": "PO Box 70962",
    "JOIN_DATE": "16/8/2023 00:00:00",
    "PHOTO": "https://robohash.org/debitisdeserunttemporibus.png?size=50x50&set=set1"
  },
  {
    "E_ID": 8.0,
    "E_NAME": "Carley",
    "USER_NAME": "chartle7",
    "PASSWORD": "kR0#2h*L",
    "PHONE_NO": "912-425-3900",
    "EMAIL": "chinkens7@icq.com",
    "ADDRESS": "Room 1873",
    "JOIN_DATE": "29/5/2023 00:00:00",
    "PHOTO": "https://robohash.org/nostrumcorporisut.png?size=50x50&set=set1"
  },
  {
    "E_ID": 9.0,
    "E_NAME": "Irving",
    "USER_NAME": "imaccaig8",
    "PASSWORD": "hW6?r>@Iasd>",
    "PHONE_NO": "605-686-7189",
    "EMAIL": "ikenrick8@ow.ly",
    "ADDRESS": "Suite 3",
    "JOIN_DATE": "27/7/2023 00:00:00",
    "PHOTO": "https://robohash.org/iuredoloremqueesse.png?size=50x50&set=set1"
  },
  {
    "E_ID": 10.0,
    "E_NAME": "Bendite",
    "USER_NAME": "bpetrus9",
    "PASSWORD": "yP6/Z?,{=*7",
    "PHONE_NO": "745-826-2698",
    "EMAIL": "bceeley9@businessweek.com",
    "ADDRESS": "14th Floor",
    "JOIN_DATE": "30/7/2023 00:00:00",
    "PHOTO": "https://robohash.org/itaqueautvelit.png?size=50x50&set=set1"
  },
  {
    "E_ID": 11.0,
    "E_NAME": "Eugen",
    "USER_NAME": "eyakuntsova",
    "PASSWORD": "oT0\\2U8d=Q6",
    "PHONE_NO": "910-776-9347",
    "EMAIL": "eshieldsa@sciencedirect.com",
    "ADDRESS": "Suite 54",
    "JOIN_DATE": "19/4/2023 00:00:00",
    "PHOTO": "https://robohash.org/etoditmolestiae.png?size=50x50&set=set1"
  },
  {
    "E_ID": 12.0,
    "E_NAME": "Maribel",
    "USER_NAME": "mnancarrowb",
    "PASSWORD": "fI3|G~i!lLq=E",
    "PHONE_NO": "709-834-2774",
    "EMAIL": "mclissb@mail.ru",
    "ADDRESS": "Suite 10",
    "JOIN_DATE": "7/8/2022 00:00:00",
    "PHOTO": "https://robohash.org/fugitomnisnon.png?size=50x50&set=set1"
  },
  {
    "E_ID": 13.0,
    "E_NAME": "Isabel",
    "USER_NAME": "idavidowc",
    "PASSWORD": "rK3\\Wh7zADB&wFR",
    "PHONE_NO": "379-926-2937",
    "EMAIL": "igoffec@loc.gov",
    "ADDRESS": "Apt 1478",
    "JOIN_DATE": "1/1/2023 00:00:00",
    "PHOTO": "https://robohash.org/eniminventorelaboriosam.png?size=50x50&set=set1"
  },
  {
    "E_ID": 14.0,
    "E_NAME": "Luigi",
    "USER_NAME": "lgilveard",
    "PASSWORD": "zE0?T2_q%{,p?>\"G",
    "PHONE_NO": "121-754-1170",
    "EMAIL": "lbardd@aboutads.info",
    "ADDRESS": "5th Floor",
    "JOIN_DATE": "5/3/2023 00:00:00",
    "PHOTO": "https://robohash.org/utculpadolor.png?size=50x50&set=set1"
  },
  {
    "E_ID": 15.0,
    "E_NAME": "Madeleine",
    "USER_NAME": "mstirgesse",
    "PASSWORD": "qK7\"B%w%x",
    "PHONE_NO": "490-861-7229",
    "EMAIL": "mmulveye@va.gov",
    "ADDRESS": "PO Box 55012",
    "JOIN_DATE": "30/8/2022 00:00:00",
    "PHOTO": "https://robohash.org/eligendietvel.png?size=50x50&set=set1"
  },
  {
    "E_ID": 16.0,
    "E_NAME": "Rollie",
    "USER_NAME": "rrabjohnsf",
    "PASSWORD": "cU3@_x./yF",
    "PHONE_NO": "441-528-8178",
    "EMAIL": "rdwyerf@vimeo.com",
    "ADDRESS": "PO Box 65857",
    "JOIN_DATE": "7/6/2022 00:00:00",
    "PHOTO": "https://robohash.org/liberoofficiisasperiores.png?size=50x50&set=set1"
  },
  {
    "E_ID": 17.0,
    "E_NAME": "Averill",
    "USER_NAME": "aferrimang",
    "PASSWORD": "uH5(RULi2WMC!r",
    "PHONE_NO": "819-280-4105",
    "EMAIL": "afranklandg@free.fr",
    "ADDRESS": "Room 1099",
    "JOIN_DATE": "22/7/2022 00:00:00",
    "PHOTO": "https://robohash.org/consequaturaliquamvitae.png?size=50x50&set=set1"
  },
  {
    "E_ID": 18.0,
    "E_NAME": "Moishe",
    "USER_NAME": "mpriestmanh",
    "PASSWORD": "aT7~4cckdN@>H4",
    "PHONE_NO": "394-929-7135",
    "EMAIL": "mrossanth@webs.com",
    "ADDRESS": "Apt 341",
    "JOIN_DATE": "12/6/2023 00:00:00",
    "PHOTO": "https://robohash.org/etdignissimosenim.png?size=50x50&set=set1"
  },
  {
    "E_ID": 19.0,
    "E_NAME": "Osgood",
    "USER_NAME": "onataliei",
    "PASSWORD": "yG2`j~RQ",
    "PHONE_NO": "284-722-0977",
    "EMAIL": "ogellioni@reuters.com",
    "ADDRESS": "Room 319",
    "JOIN_DATE": "22/11/2022 00:00:00",
    "PHOTO": "https://robohash.org/quaeratutconsequatur.png?size=50x50&set=set1"
  },
  {
    "E_ID": 20.0,
    "E_NAME": "Tiebout",
    "USER_NAME": "tstanelandj",
    "PASSWORD": "aB2&,jD6|Z.#",
    "PHONE_NO": "221-949-5484",
    "EMAIL": "tcurtinj@who.int",
    "ADDRESS": "Suite 31",
    "JOIN_DATE": "14/4/2022 00:00:00",
    "PHOTO": "https://robohash.org/nesciuntdeseruntodio.png?size=50x50&set=set1"
  },
  {
    "E_ID": 21.0,
    "E_NAME": "Mikkel",
    "USER_NAME": "msimank",
    "PASSWORD": "xC5'KaTsQ",
    "PHONE_NO": "901-648-7428",
    "EMAIL": "mwynnk@newyorker.com",
    "ADDRESS": "Suite 47",
    "JOIN_DATE": "3/4/2022 00:00:00",
    "PHOTO": "https://robohash.org/necessitatibusdolorcumque.png?size=50x50&set=set1"
  },
  {
    "E_ID": 22.0,
    "E_NAME": "Adeline",
    "USER_NAME": "aaubreyl",
    "PASSWORD": "hM8&S)CP",
    "PHONE_NO": "305-968-5947",
    "EMAIL": "aspiersl@facebook.com",
    "ADDRESS": "PO Box 466",
    "JOIN_DATE": "5/3/2023 00:00:00",
    "PHOTO": "https://robohash.org/minusutpossimus.png?size=50x50&set=set1"
  },
  {
    "E_ID": 23.0,
    "E_NAME": "Lin",
    "USER_NAME": "lkleem",
    "PASSWORD": "oU6/\"#Pr",
    "PHONE_NO": "842-512-3186",
    "EMAIL": "lknowlysm@vkontakte.ru",
    "ADDRESS": "PO Box 82105",
    "JOIN_DATE": "28/6/2022 00:00:00",
    "PHOTO": "https://robohash.org/rerumconsecteturconsequatur.png?size=50x50&set=set1"
  },
  {
    "E_ID": 24.0,
    "E_NAME": "Arte",
    "USER_NAME": "amacronaldn",
    "PASSWORD": "fH9%,/z4T9v29&",
    "PHONE_NO": "184-169-9708",
    "EMAIL": "awaddyn@slideshare.net",
    "ADDRESS": "16th Floor",
    "JOIN_DATE": "1/5/2023 00:00:00",
    "PHOTO": "https://robohash.org/eumlaudantiumtenetur.png?size=50x50&set=set1"
  },
  {
    "E_ID": 25.0,
    "E_NAME": "Merry",
    "USER_NAME": "mbelamyo",
    "PASSWORD": "qS6<fna}Wc'Z@io",
    "PHONE_NO": "994-920-4849",
    "EMAIL": "mwilbrahamo@booking.com",
    "ADDRESS": "PO Box 82368",
    "JOIN_DATE": "17/7/2022 00:00:00",
    "PHOTO": "https://robohash.org/numquameligendirerum.png?size=50x50&set=set1"
  }
]